pptx_editor/__init__.py
pptx_editor/editor.py
pptx_editor-0.1.2.dist-info/METADATA
pptx_editor-0.1.2.dist-info/WHEEL
pptx_editor-0.1.2.dist-info/top_level.txt
pptx_editor-0.1.2.dist-info/RECORD
