Metadata-Version: 2.2
Name: pptx-editor
Version: 0.1.2
Summary: A Python library for navigating PowerPoint slides and adding a red dot
Home-page: https://github.com/yourusername/pptx_editor
Author: Your Name
Author-email: your.email@example.com
Classifier: Programming Language :: Python :: 3
Classifier: License :: OSI Approved :: MIT License
Classifier: Operating System :: OS Independent
Requires-Python: >=3.6
Requires-Dist: python-pptx
Dynamic: author
Dynamic: author-email
Dynamic: classifier
Dynamic: description
Dynamic: description-content-type
Dynamic: home-page
Dynamic: requires-dist
Dynamic: requires-python
Dynamic: summary
